{
  "packageDirectories": [
    {
      "versionName": "ver 0.1",
      "versionNumber": "0.1.0.NEXT",
      "path": "force-app",
      "default": true,
      "package": "agent-assist-experimental",
      "versionDescription": "",
      "postInstallScript": "PostInstallScript"
    }
  ],
  "name": "sf-package-dev-lab",
  "namespace": "agent_assist",
  "sfdcLoginUrl": "https://login.salesforce.com",
  "sourceApiVersion": "64.0",
  "packageAliases": {
    "agent-assist-experimental": "0Hoao0000002pxhCAA"
  }
}